LICENSE
README.rst
requirements.txt
setup.py
fio_area/__init__.py
fio_area/utils.py
fio_area.egg-info/PKG-INFO
fio_area.egg-info/SOURCES.txt
fio_area.egg-info/dependency_links.txt
fio_area.egg-info/entry_points.txt
fio_area.egg-info/not-zip-safe
fio_area.egg-info/requires.txt
fio_area.egg-info/top_level.txt
fio_area/scripts/__init__.py
fio_area/scripts/cli.py