Metadata-Version: 1.1
Name: fio-area
Version: 0.1.0
Summary: Fiona CLI plugin to calculate areas
Home-page: https://github.com/mapbox/fio-area
Author: Damon Burgett
Author-email: damon@mapbox.com
License: BSD
Keywords: fiona
Platform: UNKNOWN
Classifier: Topic :: Scientific/Engineering :: GIS
Classifier: Programming Language :: Python :: 2.7
Classifier: Programming Language :: Python :: 3.6
